rewind/__init__.py
rewind/extract.py
rewind/request.py
rewind/rewind.py
rewind/youtube.py
pyrewind-0.0.1.dist-info/LICENSE
pyrewind-0.0.1.dist-info/METADATA
pyrewind-0.0.1.dist-info/WHEEL
pyrewind-0.0.1.dist-info/top_level.txt
pyrewind-0.0.1.dist-info/RECORD
