Metadata-Version: 2.1
Name: pyrewind
Version: 0.0.1
Summary: PyRewind es una poderosa librería de Python diseñada para facilitar la obtención y descarga de videos que han sido eliminados anteriormente en YouTube.
Home-page: https://github.com/fcoagz/pyBCV
Author: Francisco Griman
Author-email: Francisco Griman <grihardware@gmail.com>
License: MIT
Project-URL: Homepage, https://github.com/fcoagz/rewind
Project-URL: Bug Tracker, https://github.com/fcoagz/rewind/issues
Keywords: youtube,youtube-dl,video delete,download,video
Classifier: Programming Language :: Python :: 3
Classifier: License :: OSI Approved :: MIT License
Classifier: Operating System :: OS Independent
Requires-Python: >=3.8
License-File: LICENSE
Requires-Dist: requests
Requires-Dist: bs4
Requires-Dist: BeautifulSoup
Requires-Dist: PyYAML
Requires-Dist: pytube
Requires-Dist: tqdm
